<BackupInst xmlns="http://www.microsoft.com/GroupPolicy/GPOOperations/Manifest"><GPOGuid><![CDATA[{f37d7128-ae90-4015-bc69-ade5300141d5}]]></GPOGuid><GPODomain><![CDATA[corp.fabrikam.com]]></GPODomain><GPODomainGuid><![CDATA[{392217a3-8119-47ee-ae41-50b8a7144a3c}]]></GPODomainGuid><GPODomainController><![CDATA[FAB-DC07.corp.fabrikam.com]]></GPODomainController><BackupTime><![CDATA[2025-04-30T19:35:49]]></BackupTime><ID><![CDATA[{41E3C4BF-63FD-420C-890D-C5EB5AE4936B}]]></ID><Comment><![CDATA[]]></Comment><GPODisplayName><![CDATA[Windows Update Policy - Slot 20]]></GPODisplayName></BackupInst>
