<BackupInst xmlns="http://www.microsoft.com/GroupPolicy/GPOOperations/Manifest"><GPOGuid><![CDATA[{cff636aa-24e1-4919-9290-2c2d55953051}]]></GPOGuid><GPODomain><![CDATA[corp.contoso.com]]></GPODomain><GPODomainGuid><![CDATA[{23ab8f37-732c-4394-a64c-c963e83bada0}]]></GPODomainGuid><GPODomainController><![CDATA[CON-DC07.corp.contoso.com]]></GPODomainController><BackupTime><![CDATA[2025-05-14T14:39:26]]></BackupTime><ID><![CDATA[{D485DC9B-F7F2-4EE7-8CC0-F0789389B4C4}]]></ID><Comment><![CDATA[]]></Comment><GPODisplayName><![CDATA[Windows Update Policy - Slot 21]]></GPODisplayName></BackupInst>
